{
  "$keywords": {
    "hostNames": {
      "propertyParameters": {
        "value": {
          "type": "string"
        }
      },
      "array": true
    },
    "pfxBlob": {
      "propertyParameters": {
        "value": {
          "type": "string"
        }
      }
    },
    "password": {
      "propertyParameters": {
        "value": {
          "type": "string"
        }
      }
    },
    "keyVaultId": {
      "propertyParameters": {
        "value": {
          "type": "string"
        }
      }
    },
    "keyVaultSecretName": {
      "propertyParameters": {
        "value": {
          "type": "string"
        }
      }
    },
    "serverFarmId": {
      "propertyParameters": {
        "value": {
          "type": "string"
        }
      }
    },
    "name": {
      "propertyParameters": {
        "value": {
          "type": "string"
        }
      }
    },
    "publishingUserName": {
      "propertyParameters": {
        "value": {
          "type": "string"
        }
      }
    },
    "publishingPassword": {
      "propertyParameters": {
        "value": {
          "type": "string"
        }
      }
    },
    "publishingPasswordHash": {
      "propertyParameters": {
        "value": {
          "type": "string"
        }
      }
    },
    "publishingPasswordHashSalt": {
      "propertyParameters": {
        "value": {
          "type": "string"
        }
      }
    },
    "name_1": {
      "propertyParameters": {
        "value": {
          "type": "string"
        }
      }
    },
    "token": {
      "propertyParameters": {
        "value": {
          "type": "string"
        }
      }
    },
    "tokenSecret": {
      "propertyParameters": {
        "value": {
          "type": "string"
        }
      }
    },
    "refreshToken": {
      "propertyParameters": {
        "value": {
          "type": "string"
        }
      }
    },
    "expirationTime": {
      "propertyParameters": {
        "value": {
          "type": "string"
        }
      }
    }
  },
  "$resources": {
    "certificates": {
      "hostNames": {
        "$ref": "#/$keywords/hostNames"
      },
      "pfxBlob": {
        "$ref": "#/$keywords/pfxBlob"
      },
      "password": {
        "$ref": "#/$keywords/password"
      },
      "keyVaultId": {
        "$ref": "#/$keywords/keyVaultId"
      },
      "keyVaultSecretName": {
        "$ref": "#/$keywords/keyVaultSecretName"
      },
      "serverFarmId": {
        "$ref": "#/$keywords/serverFarmId"
      }
    },
    "publishingUsers": {
      "name": {
        "$ref": "#/$keywords/name"
      },
      "publishingUserName": {
        "$ref": "#/$keywords/publishingUserName"
      },
      "publishingPassword": {
        "$ref": "#/$keywords/publishingPassword"
      },
      "publishingPasswordHash": {
        "$ref": "#/$keywords/publishingPasswordHash"
      },
      "publishingPasswordHashSalt": {
        "$ref": "#/$keywords/publishingPasswordHashSalt"
      }
    },
    "sourcecontrols": {
      "name": {
        "$ref": "#/$keywords/name_1"
      },
      "token": {
        "$ref": "#/$keywords/token"
      },
      "tokenSecret": {
        "$ref": "#/$keywords/tokenSecret"
      },
      "refreshToken": {
        "$ref": "#/$keywords/refreshToken"
      },
      "expirationTime": {
        "$ref": "#/$keywords/expirationTime"
      }
    }
  }
}
