{
  "$keywords": {
    "status": {
      "propertyParameters": {
        "value": {
          "type": "string",
          "enum": [
            "Disabled",
            "Enabled"
          ]
        }
      }
    },
    "platform": {
      "body": {
        "os": {
          "$ref": "#/$keywords/os"
        },
        "architecture": {
          "$ref": "#/$keywords/architecture"
        },
        "variant": {
          "$ref": "#/$keywords/variant"
        }
      }
    },
    "os": {
      "propertyParameters": {
        "value": {
          "type": "string",
          "enum": [
            "Windows",
            "Linux"
          ]
        }
      }
    },
    "architecture": {
      "propertyParameters": {
        "value": {
          "type": "string",
          "enum": [
            "amd64",
            "x86",
            "arm"
          ]
        }
      }
    },
    "variant": {
      "propertyParameters": {
        "value": {
          "type": "string",
          "enum": [
            "v6",
            "v7",
            "v8"
          ]
        }
      }
    },
    "agentConfiguration": {
      "body": {
        "cpu": {
          "$ref": "#/$keywords/cpu"
        }
      }
    },
    "cpu": {
      "propertyParameters": {
        "value": {
          "type": "int",
          "default": 0
        }
      }
    },
    "timeout": {
      "propertyParameters": {
        "value": {
          "type": "int",
          "default": 3600
        }
      }
    },
    "step": {
      "body": {
        "contextPath": {
          "$ref": "#/$keywords/contextPath"
        },
        "contextAccessToken": {
          "$ref": "#/$keywords/contextAccessToken"
        }
      }
    },
    "contextPath": {
      "propertyParameters": {
        "value": {
          "type": "string"
        }
      }
    },
    "contextAccessToken": {
      "propertyParameters": {
        "value": {
          "type": "string"
        }
      }
    },
    "trigger": {
      "body": {
        "sourceTriggers": {
          "$ref": "#/$keywords/sourceTriggers"
        },
        "baseImageTrigger": {
          "$ref": "#/$keywords/baseImageTrigger"
        }
      }
    },
    "sourceTriggers": {
      "body": {
        "sourceRepository": {
          "$ref": "#/$keywords/sourceRepository"
        },
        "sourceTriggerEvents": {
          "$ref": "#/$keywords/sourceTriggerEvents"
        },
        "status": {
          "$ref": "#/$keywords/status_1"
        },
        "name": {
          "$ref": "#/$keywords/name"
        }
      },
      "array": true
    },
    "sourceRepository": {
      "body": {
        "sourceControlType": {
          "$ref": "#/$keywords/sourceControlType"
        },
        "repositoryUrl": {
          "$ref": "#/$keywords/repositoryUrl"
        },
        "branch": {
          "$ref": "#/$keywords/branch"
        },
        "sourceControlAuthProperties": {
          "$ref": "#/$keywords/sourceControlAuthProperties"
        }
      }
    },
    "sourceControlType": {
      "propertyParameters": {
        "value": {
          "type": "string",
          "enum": [
            "Github",
            "VisualStudioTeamService"
          ]
        }
      }
    },
    "repositoryUrl": {
      "propertyParameters": {
        "value": {
          "type": "string"
        }
      }
    },
    "branch": {
      "propertyParameters": {
        "value": {
          "type": "string"
        }
      }
    },
    "sourceControlAuthProperties": {
      "body": {
        "tokenType": {
          "$ref": "#/$keywords/tokenType"
        },
        "token": {
          "$ref": "#/$keywords/token"
        },
        "refreshToken": {
          "$ref": "#/$keywords/refreshToken"
        },
        "scope": {
          "$ref": "#/$keywords/scope"
        },
        "expiresIn": {
          "$ref": "#/$keywords/expiresIn"
        }
      }
    },
    "tokenType": {
      "propertyParameters": {
        "value": {
          "type": "string",
          "enum": [
            "PAT",
            "OAuth"
          ]
        }
      }
    },
    "token": {
      "propertyParameters": {
        "value": {
          "type": "string"
        }
      }
    },
    "refreshToken": {
      "propertyParameters": {
        "value": {
          "type": "string"
        }
      }
    },
    "scope": {
      "propertyParameters": {
        "value": {
          "type": "string"
        }
      }
    },
    "expiresIn": {
      "propertyParameters": {
        "value": {
          "type": "int",
          "default": 0
        }
      }
    },
    "sourceTriggerEvents": {
      "propertyParameters": {
        "value": {
          "type": "string",
          "enum": [
            "commit",
            "pullrequest"
          ]
        }
      },
      "array": true
    },
    "status_1": {
      "propertyParameters": {
        "value": {
          "type": "string",
          "enum": [
            "Disabled",
            "Enabled"
          ]
        }
      }
    },
    "name": {
      "propertyParameters": {
        "value": {
          "type": "string"
        }
      }
    },
    "baseImageTrigger": {
      "body": {
        "baseImageTriggerType": {
          "$ref": "#/$keywords/baseImageTriggerType"
        },
        "status": {
          "$ref": "#/$keywords/status_1_2"
        },
        "name": {
          "$ref": "#/$keywords/name_1"
        }
      }
    },
    "baseImageTriggerType": {
      "propertyParameters": {
        "value": {
          "type": "string",
          "enum": [
            "All",
            "Runtime"
          ]
        }
      }
    },
    "status_1_2": {
      "propertyParameters": {
        "value": {
          "type": "string",
          "enum": [
            "Disabled",
            "Enabled"
          ]
        }
      }
    },
    "name_1": {
      "propertyParameters": {
        "value": {
          "type": "string"
        }
      }
    },
    "credentials": {
      "body": {
        "sourceRegistry": {
          "$ref": "#/$keywords/sourceRegistry"
        },
        "customRegistries": {
          "$ref": "#/$keywords/customRegistries"
        }
      }
    },
    "sourceRegistry": {
      "body": {
        "loginMode": {
          "$ref": "#/$keywords/loginMode"
        }
      }
    },
    "loginMode": {
      "propertyParameters": {
        "value": {
          "type": "string",
          "enum": [
            "None",
            "Default"
          ]
        }
      }
    },
    "customRegistries": {
      "body": {}
    }
  },
  "$resources": {
    "registries/tasks": {
      "status": {
        "$ref": "#/$keywords/status"
      },
      "platform": {
        "$ref": "#/$keywords/platform"
      },
      "agentConfiguration": {
        "$ref": "#/$keywords/agentConfiguration"
      },
      "timeout": {
        "$ref": "#/$keywords/timeout"
      },
      "step": {
        "$ref": "#/$keywords/step"
      },
      "trigger": {
        "$ref": "#/$keywords/trigger"
      },
      "credentials": {
        "$ref": "#/$keywords/credentials"
      }
    }
  }
}
