{
  "$keywords": {
    "description": {
      "propertyParameters": {
        "value": {
          "type": "string"
        }
      }
    },
    "clusterType": {
      "propertyParameters": {
        "value": {
          "type": "string",
          "enum": [
            "ACS",
            "Local"
          ]
        }
      }
    },
    "storageAccount": {
      "body": {
        "resourceId": {
          "$ref": "#/$keywords/resourceId"
        }
      }
    },
    "resourceId": {
      "propertyParameters": {
        "value": {
          "type": "string"
        }
      }
    },
    "containerRegistry": {
      "body": {
        "resourceId": {
          "$ref": "#/$keywords/resourceId_1"
        }
      }
    },
    "resourceId_1": {
      "propertyParameters": {
        "value": {
          "type": "string"
        }
      }
    },
    "containerService": {
      "body": {
        "orchestratorType": {
          "$ref": "#/$keywords/orchestratorType"
        },
        "orchestratorProperties": {
          "$ref": "#/$keywords/orchestratorProperties"
        },
        "systemServices": {
          "$ref": "#/$keywords/systemServices"
        },
        "masterCount": {
          "$ref": "#/$keywords/masterCount"
        },
        "agentCount": {
          "$ref": "#/$keywords/agentCount"
        },
        "agentVmSize": {
          "$ref": "#/$keywords/agentVmSize"
        }
      }
    },
    "orchestratorType": {
      "propertyParameters": {
        "value": {
          "type": "string",
          "enum": [
            "Kubernetes",
            "None"
          ]
        }
      }
    },
    "orchestratorProperties": {
      "body": {
        "servicePrincipal": {
          "$ref": "#/$keywords/servicePrincipal"
        }
      }
    },
    "servicePrincipal": {
      "body": {
        "clientId": {
          "$ref": "#/$keywords/clientId"
        },
        "secret": {
          "$ref": "#/$keywords/secret"
        }
      }
    },
    "clientId": {
      "propertyParameters": {
        "value": {
          "type": "string"
        }
      }
    },
    "secret": {
      "propertyParameters": {
        "value": {
          "type": "string"
        }
      }
    },
    "systemServices": {
      "body": {
        "systemServiceType": {
          "$ref": "#/$keywords/systemServiceType"
        }
      },
      "array": true
    },
    "systemServiceType": {
      "propertyParameters": {
        "value": {
          "type": "string",
          "enum": [
            "None",
            "ScoringFrontEnd",
            "BatchFrontEnd"
          ]
        }
      }
    },
    "masterCount": {
      "propertyParameters": {
        "value": {
          "type": "int",
          "default": 1
        }
      }
    },
    "agentCount": {
      "propertyParameters": {
        "value": {
          "type": "int",
          "default": 2
        }
      }
    },
    "agentVmSize": {
      "propertyParameters": {
        "value": {
          "type": "string",
          "enum": [
            "Standard_A0",
            "Standard_A1",
            "Standard_A2",
            "Standard_A3",
            "Standard_A4",
            "Standard_A5",
            "Standard_A6",
            "Standard_A7",
            "Standard_A8",
            "Standard_A9",
            "Standard_A10",
            "Standard_A11",
            "Standard_D1",
            "Standard_D2",
            "Standard_D3",
            "Standard_D4",
            "Standard_D11",
            "Standard_D12",
            "Standard_D13",
            "Standard_D14",
            "Standard_D1_v2",
            "Standard_D2_v2",
            "Standard_D3_v2",
            "Standard_D4_v2",
            "Standard_D5_v2",
            "Standard_D11_v2",
            "Standard_D12_v2",
            "Standard_D13_v2",
            "Standard_D14_v2",
            "Standard_G1",
            "Standard_G2",
            "Standard_G3",
            "Standard_G4",
            "Standard_G5",
            "Standard_DS1",
            "Standard_DS2",
            "Standard_DS3",
            "Standard_DS4",
            "Standard_DS11",
            "Standard_DS12",
            "Standard_DS13",
            "Standard_DS14",
            "Standard_GS1",
            "Standard_GS2",
            "Standard_GS3",
            "Standard_GS4",
            "Standard_GS5"
          ]
        }
      }
    },
    "appInsights": {
      "body": {
        "resourceId": {
          "$ref": "#/$keywords/resourceId_1_2"
        }
      }
    },
    "resourceId_1_2": {
      "propertyParameters": {
        "value": {
          "type": "string"
        }
      }
    },
    "globalServiceConfiguration": {
      "body": {
        "additionalProperties": {
          "$ref": "#/$keywords/additionalProperties"
        },
        "etag": {
          "$ref": "#/$keywords/etag"
        },
        "ssl": {
          "$ref": "#/$keywords/ssl"
        },
        "serviceAuth": {
          "$ref": "#/$keywords/serviceAuth"
        },
        "autoScale": {
          "$ref": "#/$keywords/autoScale"
        }
      }
    },
    "additionalProperties": {
      "body": {}
    },
    "etag": {
      "propertyParameters": {
        "value": {
          "type": "string"
        }
      }
    },
    "ssl": {
      "body": {
        "status": {
          "$ref": "#/$keywords/status"
        },
        "cert": {
          "$ref": "#/$keywords/cert"
        },
        "key": {
          "$ref": "#/$keywords/key"
        },
        "cname": {
          "$ref": "#/$keywords/cname"
        }
      }
    },
    "status": {
      "propertyParameters": {
        "value": {
          "type": "string",
          "enum": [
            "Enabled",
            "Disabled"
          ]
        }
      }
    },
    "cert": {
      "propertyParameters": {
        "value": {
          "type": "string"
        }
      }
    },
    "key": {
      "propertyParameters": {
        "value": {
          "type": "string"
        }
      }
    },
    "cname": {
      "propertyParameters": {
        "value": {
          "type": "string"
        }
      }
    },
    "serviceAuth": {
      "body": {
        "primaryAuthKeyHash": {
          "$ref": "#/$keywords/primaryAuthKeyHash"
        },
        "secondaryAuthKeyHash": {
          "$ref": "#/$keywords/secondaryAuthKeyHash"
        }
      }
    },
    "primaryAuthKeyHash": {
      "propertyParameters": {
        "value": {
          "type": "string"
        }
      }
    },
    "secondaryAuthKeyHash": {
      "propertyParameters": {
        "value": {
          "type": "string"
        }
      }
    },
    "autoScale": {
      "body": {
        "status": {
          "$ref": "#/$keywords/status_1"
        },
        "minReplicas": {
          "$ref": "#/$keywords/minReplicas"
        },
        "maxReplicas": {
          "$ref": "#/$keywords/maxReplicas"
        },
        "targetUtilization": {
          "$ref": "#/$keywords/targetUtilization"
        },
        "refreshPeriodInSeconds": {
          "$ref": "#/$keywords/refreshPeriodInSeconds"
        }
      }
    },
    "status_1": {
      "propertyParameters": {
        "value": {
          "type": "string",
          "enum": [
            "Enabled",
            "Disabled"
          ]
        }
      }
    },
    "minReplicas": {
      "propertyParameters": {
        "value": {
          "type": "int",
          "default": 1
        }
      }
    },
    "maxReplicas": {
      "propertyParameters": {
        "value": {
          "type": "int",
          "default": 100
        }
      }
    },
    "targetUtilization": {
      "propertyParameters": {
        "value": {
          "type": "number",
          "default": 0.0
        }
      }
    },
    "refreshPeriodInSeconds": {
      "propertyParameters": {
        "value": {
          "type": "int",
          "default": 0
        }
      }
    }
  },
  "$resources": {
    "operationalizationClusters": {
      "description": {
        "$ref": "#/$keywords/description"
      },
      "clusterType": {
        "$ref": "#/$keywords/clusterType"
      },
      "storageAccount": {
        "$ref": "#/$keywords/storageAccount"
      },
      "containerRegistry": {
        "$ref": "#/$keywords/containerRegistry"
      },
      "containerService": {
        "$ref": "#/$keywords/containerService"
      },
      "appInsights": {
        "$ref": "#/$keywords/appInsights"
      },
      "globalServiceConfiguration": {
        "$ref": "#/$keywords/globalServiceConfiguration"
      }
    }
  }
}
