{
  "$keywords": {
    "tenantId": {
      "propertyParameters": {
        "value": {
          "type": "string"
        }
      }
    },
    "sku": {
      "body": {
        "family": {
          "$ref": "#/$keywords/family"
        },
        "name": {
          "$ref": "#/$keywords/name"
        }
      }
    },
    "family": {
      "propertyParameters": {
        "value": {
          "type": "string",
          "enum": [
            "A"
          ]
        }
      }
    },
    "name": {
      "propertyParameters": {
        "value": {
          "type": "string",
          "enum": [
            "standard",
            "premium"
          ]
        }
      }
    },
    "accessPolicies": {
      "body": {
        "tenantId": {
          "$ref": "#/$keywords/tenantId_1"
        },
        "objectId": {
          "$ref": "#/$keywords/objectId"
        },
        "applicationId": {
          "$ref": "#/$keywords/applicationId"
        },
        "permissions": {
          "$ref": "#/$keywords/permissions"
        }
      },
      "array": true
    },
    "tenantId_1": {
      "propertyParameters": {
        "value": {
          "type": "string"
        }
      }
    },
    "objectId": {
      "propertyParameters": {
        "value": {
          "type": "string"
        }
      }
    },
    "applicationId": {
      "propertyParameters": {
        "value": {
          "type": "string"
        }
      }
    },
    "permissions": {
      "body": {
        "keys": {
          "$ref": "#/$keywords/keys"
        },
        "secrets": {
          "$ref": "#/$keywords/secrets"
        },
        "certificates": {
          "$ref": "#/$keywords/certificates"
        },
        "storage": {
          "$ref": "#/$keywords/storage"
        }
      }
    },
    "keys": {
      "propertyParameters": {
        "value": {
          "type": "string",
          "enum": [
            "encrypt",
            "decrypt",
            "wrapKey",
            "unwrapKey",
            "sign",
            "verify",
            "get",
            "list",
            "create",
            "update",
            "import",
            "delete",
            "backup",
            "restore",
            "recover",
            "purge"
          ]
        }
      },
      "array": true
    },
    "secrets": {
      "propertyParameters": {
        "value": {
          "type": "string",
          "enum": [
            "get",
            "list",
            "set",
            "delete",
            "backup",
            "restore",
            "recover",
            "purge"
          ]
        }
      },
      "array": true
    },
    "certificates": {
      "propertyParameters": {
        "value": {
          "type": "string",
          "enum": [
            "get",
            "list",
            "delete",
            "create",
            "import",
            "update",
            "managecontacts",
            "getissuers",
            "listissuers",
            "setissuers",
            "deleteissuers",
            "manageissuers",
            "recover",
            "purge"
          ]
        }
      },
      "array": true
    },
    "storage": {
      "propertyParameters": {
        "value": {
          "type": "string",
          "enum": [
            "get",
            "list",
            "delete",
            "set",
            "update",
            "regeneratekey",
            "recover",
            "purge",
            "backup",
            "restore",
            "setsas",
            "listsas",
            "getsas",
            "deletesas"
          ]
        }
      },
      "array": true
    },
    "vaultUri": {
      "propertyParameters": {
        "value": {
          "type": "string"
        }
      }
    },
    "enabledForDeployment": {
      "propertyParameters": {
        "value": {
          "type": "bool",
          "default": false
        }
      }
    },
    "enabledForDiskEncryption": {
      "propertyParameters": {
        "value": {
          "type": "bool",
          "default": false
        }
      }
    },
    "enabledForTemplateDeployment": {
      "propertyParameters": {
        "value": {
          "type": "bool",
          "default": false
        }
      }
    },
    "enableSoftDelete": {
      "propertyParameters": {
        "value": {
          "type": "bool",
          "default": false
        }
      }
    },
    "createMode": {
      "propertyParameters": {
        "value": {
          "type": "string",
          "enum": [
            "recover",
            "default"
          ]
        }
      }
    },
    "enablePurgeProtection": {
      "propertyParameters": {
        "value": {
          "type": "bool",
          "default": false
        }
      }
    },
    "accessPolicies_1": {
      "body": {
        "tenantId": {
          "$ref": "#/$keywords/tenantId_1"
        },
        "objectId": {
          "$ref": "#/$keywords/objectId"
        },
        "applicationId": {
          "$ref": "#/$keywords/applicationId"
        },
        "permissions": {
          "$ref": "#/$keywords/permissions"
        }
      },
      "array": true
    }
  },
  "$resources": {
    "vaults": {
      "tenantId": {
        "$ref": "#/$keywords/tenantId"
      },
      "sku": {
        "$ref": "#/$keywords/sku"
      },
      "accessPolicies": {
        "$ref": "#/$keywords/accessPolicies"
      },
      "vaultUri": {
        "$ref": "#/$keywords/vaultUri"
      },
      "enabledForDeployment": {
        "$ref": "#/$keywords/enabledForDeployment"
      },
      "enabledForDiskEncryption": {
        "$ref": "#/$keywords/enabledForDiskEncryption"
      },
      "enabledForTemplateDeployment": {
        "$ref": "#/$keywords/enabledForTemplateDeployment"
      },
      "enableSoftDelete": {
        "$ref": "#/$keywords/enableSoftDelete"
      },
      "createMode": {
        "$ref": "#/$keywords/createMode"
      },
      "enablePurgeProtection": {
        "$ref": "#/$keywords/enablePurgeProtection"
      }
    },
    "vaults/accessPolicies": {
      "accessPolicies": {
        "$ref": "#/$keywords/accessPolicies_1"
      }
    }
  }
}
