{
  "$keywords": {
    "replicaCount": {
      "propertyParameters": {
        "value": {
          "type": "int",
          "default": 1
        }
      }
    },
    "partitionCount": {
      "propertyParameters": {
        "value": {
          "type": "int",
          "default": 1
        }
      }
    },
    "hostingMode": {
      "propertyParameters": {
        "value": {
          "type": "string",
          "enum": [
            "default",
            "highDensity"
          ]
        }
      }
    }
  },
  "$resources": {
    "searchServices": {
      "replicaCount": {
        "$ref": "#/$keywords/replicaCount"
      },
      "partitionCount": {
        "$ref": "#/$keywords/partitionCount"
      },
      "hostingMode": {
        "$ref": "#/$keywords/hostingMode"
      }
    }
  }
}
